stag_python-1.1.1.dist-info/top_level.txt
stag_python-1.1.1.dist-info/RECORD
stag_python-1.1.1.dist-info/METADATA
stag_python-1.1.1.dist-info/WHEEL
stag_python-1.1.1.dist-info/LICENSE
stag/__init__.py
stag/_core.cpython-311-aarch64-linux-musl.so
stag_python.libs/libopencv_flann-638f9f87.so.4.10.0
stag_python.libs/libopencv_imgproc-2d69c183.so.4.10.0
stag_python.libs/libstdc++-1b614e01.so.6.0.32
stag_python.libs/libopencv_core-9dd1d134.so.4.10.0
stag_python.libs/libopencv_imgcodecs-d291364c.so.4.10.0
stag_python.libs/libgcc_s-7393e603.so.1
