Metadata-Version: 2.1
Name: stag-python
Version: 1.1.1
Summary: STag - A Stable, Occlusion-Resistant Fiducial Marker System
Author-email: Manfred Stoiber <manfred.stoiber@gmail.com>
Project-URL: Homepage, https://github.com/manfredstoiber/stag-python
Classifier: Development Status :: 5 - Production/Stable
Classifier: License :: OSI Approved :: MIT License
Classifier: Operating System :: OS Independent
Classifier: Programming Language :: Python :: 3.9
Classifier: Programming Language :: Python :: 3.10
Classifier: Programming Language :: Python :: 3.11
Classifier: Programming Language :: Python :: 3.12
Classifier: Programming Language :: Python :: 3.13
Classifier: Topic :: Home Automation
Classifier: Topic :: Scientific/Engineering
Classifier: Topic :: Scientific/Engineering :: Image Recognition
Classifier: Topic :: Utilities
Requires-Python: >=3.9
License-File: submodules\pybind11\LICENSE
License-File: submodules\pybind11_opencv_numpy\LICENSE
License-File: submodules\stag\LICENSE
License-File: LICENSE
Requires-Dist: numpy
